wrangle_in_py/__init__.py
wrangle_in_py/column_drop_threshold.py
wrangle_in_py/column_name_standardizer.py
wrangle_in_py/extracting_ymd_hms.py
wrangle_in_py/remove_duplicates.py
wrangle_in_py-0.0.4.dist-info/LICENSE
wrangle_in_py-0.0.4.dist-info/METADATA
wrangle_in_py-0.0.4.dist-info/WHEEL
wrangle_in_py-0.0.4.dist-info/RECORD
