Metadata-Version: 2.3
Name: wrangle_in_py
Version: 0.0.4
Summary: A package for wrangling and tidy data in python.
License: MIT
Author: Shannon Pflueger, Stephanie Ta, Wai Ming Wong, Yixuan(Clara) Gao
Requires-Python: >=3.11
Classifier: License :: OSI Approved :: MIT License
Classifier: Programming Language :: Python :: 3
Classifier: Programming Language :: Python :: 3.11
Classifier: Programming Language :: Python :: 3.12
Classifier: Programming Language :: Python :: 3.13
Requires-Dist: pandas (>=2.2.3)
Requires-Dist: scipy (>=1.15.1)
